django_mjml_template/__init__.py
django_mjml_template/apps.py
django_mjml_template/templatetags/__init__.py
django_mjml_template/templatetags/mjml.py
django_mjml_template-1.0.0.dist-info/licenses/LICENSE
django_mjml_template-1.0.0.dist-info/WHEEL
django_mjml_template-1.0.0.dist-info/METADATA
django_mjml_template-1.0.0.dist-info/RECORD
