Metadata-Version: 2.4
Name: django-mjml-template
Version: 1.0.0
Summary: Simple and fast MJML rendering for Django templates.
Keywords: django,mjml,template
Author-email: Thomas Edvalson <machin3@gmail.com>
Requires-Python: >=3.7
Classifier: Framework :: Django
Classifier: Framework :: Django :: 1.11
Classifier: Framework :: Django :: 2.2
Classifier: Framework :: Django :: 3.2
Classifier: Framework :: Django :: 4.0
Classifier: Framework :: Django :: 4.1
Classifier: Framework :: Django :: 4.2
Classifier: Framework :: Django :: 5.0
Classifier: Framework :: Django :: 5.1
Classifier: Framework :: Django :: 5.2
Classifier: Intended Audience :: Developers
Classifier: License :: OSI Approved :: MIT License
Classifier: Operating System :: OS Independent
Classifier: Programming Language :: Python
Classifier: Programming Language :: Python :: 3
Classifier: Programming Language :: Python :: 3 :: Only
Classifier: Programming Language :: Python :: 3.7
Classifier: Programming Language :: Python :: 3.8
Classifier: Programming Language :: Python :: 3.9
Classifier: Programming Language :: Python :: 3.10
Classifier: Programming Language :: Python :: 3.11
Classifier: Programming Language :: Python :: 3.12
Classifier: Topic :: Internet :: WWW/HTTP
License-File: LICENSE
Requires-Dist: mjml-python>=1.3.5
Requires-Dist: django>=1.11
Project-URL: Homepage, https://github.com/Cruel/django-mjml-template
Project-URL: Issues, https://github.com/Cruel/django-mjml-template/issues/
